ctyped/__init__.py
ctyped/exceptions.py
ctyped/library.py
ctyped/sniffer.py
ctyped/toolbox.py
ctyped/types.py
ctyped/utils.py
ctyped-0.8.0.dist-info/DESCRIPTION.rst
ctyped-0.8.0.dist-info/METADATA
ctyped-0.8.0.dist-info/RECORD
ctyped-0.8.0.dist-info/WHEEL
ctyped-0.8.0.dist-info/metadata.json
ctyped-0.8.0.dist-info/top_level.txt
